{"v":3,"stories":{"meridian-ui-getting-started-introduction--docs":{"id":"meridian-ui-getting-started-introduction--docs","title":"meridian-ui/Getting Started/Introduction","name":"Docs","importPath":"./src/Introduction.mdx","storiesImports":[],"tags":["unattached-mdx","docs"],"kind":"meridian-ui/Getting Started/Introduction","story":"Docs","parameters":{"__id":"meridian-ui-getting-started-introduction--docs","docsOnly":true,"fileName":"./src/Introduction.mdx"}},"meridian-ui-navigation-button--docs":{"id":"meridian-ui-navigation-button--docs","title":"meridian-ui/Navigation/Button","name":"Docs","importPath":"./src/components/Button/Button.stories.ts","tags":["autodocs","docs"],"storiesImports":[],"kind":"meridian-ui/Navigation/Button","story":"Docs","parameters":{"__id":"meridian-ui-navigation-button--docs","docsOnly":true,"fileName":"./src/components/Button/Button.stories.ts"}},"meridian-ui-navigation-button--primary":{"id":"meridian-ui-navigation-button--primary","title":"meridian-ui/Navigation/Button","name":"Primary","importPath":"./src/components/Button/Button.stories.ts","tags":["autodocs","story"],"kind":"meridian-ui/Navigation/Button","story":"Primary","parameters":{"__id":"meridian-ui-navigation-button--primary","docsOnly":false,"fileName":"./src/components/Button/Button.stories.ts"}},"meridian-ui-navigation-button--secondary":{"id":"meridian-ui-navigation-button--secondary","title":"meridian-ui/Navigation/Button","name":"Secondary","importPath":"./src/components/Button/Button.stories.ts","tags":["autodocs","story"],"kind":"meridian-ui/Navigation/Button","story":"Secondary","parameters":{"__id":"meridian-ui-navigation-button--secondary","docsOnly":false,"fileName":"./src/components/Button/Button.stories.ts"}},"meridian-ui-navigation-button--large":{"id":"meridian-ui-navigation-button--large","title":"meridian-ui/Navigation/Button","name":"Large","importPath":"./src/components/Button/Button.stories.ts","tags":["autodocs","story"],"kind":"meridian-ui/Navigation/Button","story":"Large","parameters":{"__id":"meridian-ui-navigation-button--large","docsOnly":false,"fileName":"./src/components/Button/Button.stories.ts"}},"meridian-ui-navigation-button--small":{"id":"meridian-ui-navigation-button--small","title":"meridian-ui/Navigation/Button","name":"Small","importPath":"./src/components/Button/Button.stories.ts","tags":["autodocs","story"],"kind":"meridian-ui/Navigation/Button","story":"Small","parameters":{"__id":"meridian-ui-navigation-button--small","docsOnly":false,"fileName":"./src/components/Button/Button.stories.ts"}},"meridian-ui-layout-header--docs":{"id":"meridian-ui-layout-header--docs","title":"meridian-ui/Layout/Header","name":"Docs","importPath":"./src/components/Header/Header.stories.ts","tags":["autodocs","docs"],"storiesImports":[],"kind":"meridian-ui/Layout/Header","story":"Docs","parameters":{"__id":"meridian-ui-layout-header--docs","docsOnly":true,"fileName":"./src/components/Header/Header.stories.ts"}},"meridian-ui-layout-header--logged-in":{"id":"meridian-ui-layout-header--logged-in","title":"meridian-ui/Layout/Header","name":"Logged In","importPath":"./src/components/Header/Header.stories.ts","tags":["autodocs","story"],"kind":"meridian-ui/Layout/Header","story":"Logged In","parameters":{"__id":"meridian-ui-layout-header--logged-in","docsOnly":false,"fileName":"./src/components/Header/Header.stories.ts"}},"meridian-ui-layout-header--logged-out":{"id":"meridian-ui-layout-header--logged-out","title":"meridian-ui/Layout/Header","name":"Logged Out","importPath":"./src/components/Header/Header.stories.ts","tags":["autodocs","story"],"kind":"meridian-ui/Layout/Header","story":"Logged Out","parameters":{"__id":"meridian-ui-layout-header--logged-out","docsOnly":false,"fileName":"./src/components/Header/Header.stories.ts"}}}}
